pybuild/__init__.py
pybuild/environment.py
pybuild/git/__init__.py
pybuild/pdoc/__init__.py
pybuild/pip/__init__.py
pybuild/pyinstaller/__init__.py
pybuild/utils/__init__.py
pybuild/utils/file_utils.py
pybuild/utils/os_utils.py
pybuild/utils/process_utils.py
pybuild/virtualenv/__init__.py
tests/__init__.py
tests/test_env.py
tests/test_git.py
tests/test_pdoc.py
tests/test_pip.py
tests/test_pyinstaller.py
tests/test_suite.py
tests/test_utils.py
tests/test_virtualenv.py
pybuildme-0.3.4.dist-info/LICENSE.txt
pybuildme-0.3.4.dist-info/METADATA
pybuildme-0.3.4.dist-info/WHEEL
pybuildme-0.3.4.dist-info/top_level.txt
pybuildme-0.3.4.dist-info/RECORD
