Metadata-Version: 2.1
Name: pybuildme
Version: 0.3.4
Summary: PyBuild is a build environment for Python that starts from the virtual environment upwards, must be installed on base system prior to running.
Home-page: https://github.com/IAmAbszol/PyBuild
Author: Kyle Darling
Author-email: kdarling95@yahoo.com
License: MIT
Keywords: build,python,automation,git,framework
Platform: UNKNOWN
Requires-Python: >=3.7
License-File: LICENSE.txt
